MANIFEST.in
README.rst
requirements.txt
setup.cfg
setup.py
djmicrosip_exportaimportaprecios/__init__.py
djmicrosip_exportaimportaprecios/__init__.pyc
djmicrosip_exportaimportaprecios/config.pyc
djmicrosip_exportaimportaprecios/forms.pyc
djmicrosip_exportaimportaprecios/models.pyc
djmicrosip_exportaimportaprecios/urls.pyc
djmicrosip_exportaimportaprecios/views.pyc
djmicrosip_exportaimportaprecios.egg-info/PKG-INFO
djmicrosip_exportaimportaprecios.egg-info/SOURCES.txt
djmicrosip_exportaimportaprecios.egg-info/dependency_links.txt
djmicrosip_exportaimportaprecios.egg-info/requires.txt
djmicrosip_exportaimportaprecios.egg-info/top_level.txt
djmicrosip_exportaimportaprecios/static/djmicrosip_exportaimportaprecios/js/core.js
djmicrosip_exportaimportaprecios/templates/djmicrosip_exportaimportaprecios/base.html
djmicrosip_exportaimportaprecios/templates/djmicrosip_exportaimportaprecios/exportar_precios.html
djmicrosip_exportaimportaprecios/templates/djmicrosip_exportaimportaprecios/importar_precios.html
djmicrosip_exportaimportaprecios/templates/djmicrosip_exportaimportaprecios/index.html
djmicrosip_exportaimportaprecios/templates/djmicrosip_exportaimportaprecios/preferencias.html